sagerender/__init__.py
sagerender/builder/__init__.py
sagerender/builder/blueprint.py
sagerender/builder/pipeline.py
sagerender/builder/step.py
sagerender/cli/__init__.py
sagerender/cli/commands.py
sagerender/cli/run_pipeline.py
sagerender/cli/upsert_pipeline.py
sagerender/cli/version.py
sagerender/defaults.py
sagerender/exceptions.py
sagerender/utilities/__init__.py
sagerender/utilities/common.py
sagerender/utilities/mixin.py
sagerender-2.1.3.dist-info/LICENSE.md
sagerender-2.1.3.dist-info/METADATA
sagerender-2.1.3.dist-info/WHEEL
sagerender-2.1.3.dist-info/entry_points.txt
sagerender-2.1.3.dist-info/RECORD
