Metadata-Version: 2.1
Name: sagerender
Version: 2.1.3
Summary: A library for configuring SageMaker pipelines using hierarchical configuration pattern.
Home-page: https://github.com/Nike-Inc/sagerender
License: Apache-2.0
Keywords: phiera,sagemaker-sdk,sagerender
Author: Mohamed Abdul Huq Ismail
Author-email: Abdul.Ismail@nike.com
Maintainer: Divyanshu Narendra
Maintainer-email: Divyanshu.Narendra@nike.com
Requires-Python: >=3.10.10,<4.0.0
Classifier: License :: OSI Approved :: Apache Software License
Classifier: Programming Language :: Python :: 3
Classifier: Programming Language :: Python :: 3.11
Requires-Dist: PyYAML (>=6.0.1,<7.0.0)
Requires-Dist: boto3 (>=1.34.55,<2.0.0)
Requires-Dist: botocore (>=1.34.55,<2.0.0)
Requires-Dist: cerberus-python-client (>=2.5.4,<3.0.0)
Requires-Dist: multipledispatch (>=1.0.0,<2.0.0)
Requires-Dist: phiera (>=2.1.0,<3.0.0)
Requires-Dist: pydantic (>=2.6.3,<3.0.0)
Requires-Dist: sagemaker (>=2.211.0,<3.0.0)
Project-URL: Repository, https://github.com/Nike-Inc/sagerender
